{
    "#003366": [
        296,
        380
    ],
    "#336699": [
        314,
        380
    ],
    "#3366CC": [
        332,
        380
    ],
    "#003399": [
        350,
        380
    ],
    "#000099": [
        368,
        380
    ],
    "#0000CC": [
        386,
        380
    ],
    "#000066": [
        404,
        380
    ],
    "#006666": [
        287,
        365
    ],
    "#006699": [
        305,
        365
    ],
    "#0099CC": [
        323,
        365
    ],
    "#0066CC": [
        341,
        365
    ],
    "#0033CC": [
        359,
        365
    ],
    "#0000FF": [
        377,
        365
    ],
    "#3333FF": [
        395,
        365
    ],
    "#333399": [
        413,
        365
    ],
    "#669999": [
        278,
        350
    ],
    "#009999": [
        296,
        350
    ],
    "#33CCCC": [
        314,
        350
    ],
    "#00CCFF": [
        332,
        350
    ],
    "#0099FF": [
        350,
        350
    ],
    "#0066FF": [
        368,
        350
    ],
    "#3366FF": [
        386,
        350
    ],
    "#3333CC": [
        404,
        350
    ],
    "#666699": [
        422,
        350
    ],
    "#339966": [
        269,
        335
    ],
    "#00CC99": [
        287,
        335
    ],
    "#00FFCC": [
        305,
        335
    ],
    "#00FFFF": [
        323,
        335
    ],
    "#33CCFF": [
        341,
        335
    ],
    "#3399FF": [
        359,
        335
    ],
    "#6699FF": [
        377,
        335
    ],
    "#6666FF": [
        395,
        335
    ],
    "#6600FF": [
        413,
        335
    ],
    "#6600CC": [
        431,
        335
    ],
    "#339933": [
        260,
        320
    ],
    "#00CC66": [
        278,
        320
    ],
    "#00FF99": [
        296,
        320
    ],
    "#66FFCC": [
        314,
        320
    ],
    "#66FFFF": [
        332,
        320
    ],
    "#66CCFF": [
        350,
        320
    ],
    "#99CCFF": [
        368,
        320
    ],
    "#9999FF": [
        386,
        320
    ],
    "#9966FF": [
        404,
        320
    ],
    "#9933FF": [
        422,
        320
    ],
    "#9900FF": [
        440,
        320
    ],
    "#006600": [
        251,
        305
    ],
    "#00CC00": [
        269,
        305
    ],
    "#00FF00": [
        287,
        305
    ],
    "#66FF99": [
        305,
        305
    ],
    "#99FFCC": [
        323,
        305
    ],
    "#CCFFFF": [
        341,
        305
    ],
    "#CCCCFF": [
        359,
        305
    ],
    "#CC99FF": [
        377,
        305
    ],
    "#CC66FF": [
        395,
        305
    ],
    "#CC33FF": [
        413,
        305
    ],
    "#CC00FF": [
        431,
        305
    ],
    "#9900CC": [
        449,
        305
    ],
    "#003300": [
        242,
        290
    ],
    "#009933": [
        260,
        290
    ],
    "#33CC33": [
        278,
        290
    ],
    "#66FF66": [
        296,
        290
    ],
    "#99FF99": [
        314,
        290
    ],
    "#CCFFCC": [
        332,
        290
    ],
    "#FFFFFF": [
        350,
        290
    ],
    "#FFCCFF": [
        368,
        290
    ],
    "#FF99FF": [
        386,
        290
    ],
    "#FF66FF": [
        404,
        290
    ],
    "#FF00FF": [
        422,
        290
    ],
    "#CC00CC": [
        440,
        290
    ],
    "#660066": [
        458,
        290
    ],
    "#336600": [
        251,
        275
    ],
    "#009900": [
        269,
        275
    ],
    "#66FF33": [
        287,
        275
    ],
    "#99FF66": [
        305,
        275
    ],
    "#CCFF99": [
        323,
        275
    ],
    "#FFFFCC": [
        341,
        275
    ],
    "#FFCCCC": [
        359,
        275
    ],
    "#FF99CC": [
        377,
        275
    ],
    "#FF66CC": [
        395,
        275
    ],
    "#FF33CC": [
        413,
        275
    ],
    "#CC0099": [
        431,
        275
    ],
    "#993399": [
        449,
        275
    ],
    "#333300": [
        260,
        260
    ],
    "#669900": [
        278,
        260
    ],
    "#99FF33": [
        296,
        260
    ],
    "#CCFF66": [
        314,
        260
    ],
    "#FFFF99": [
        332,
        260
    ],
    "#FFCC99": [
        350,
        260
    ],
    "#FF9999": [
        368,
        260
    ],
    "#FF6699": [
        386,
        260
    ],
    "#FF3399": [
        404,
        260
    ],
    "#CC3399": [
        422,
        260
    ],
    "#990099": [
        440,
        260
    ],
    "#666633": [
        269,
        245
    ],
    "#99CC00": [
        287,
        245
    ],
    "#CCFF33": [
        305,
        245
    ],
    "#FFFF66": [
        323,
        245
    ],
    "#FFCC66": [
        341,
        245
    ],
    "#FF9966": [
        359,
        245
    ],
    "#FF6666": [
        377,
        245
    ],
    "#FF0066": [
        395,
        245
    ],
    "#CC6699": [
        413,
        245
    ],
    "#993366": [
        431,
        245
    ],
    "#999966": [
        278,
        230
    ],
    "#CCCC00": [
        296,
        230
    ],
    "#FFFF00": [
        314,
        230
    ],
    "#FFCC00": [
        332,
        230
    ],
    "#FF9933": [
        350,
        230
    ],
    "#FF6600": [
        368,
        230
    ],
    "#FF5050": [
        386,
        230
    ],
    "#CC0066": [
        404,
        230
    ],
    "#660033": [
        422,
        230
    ],
    "#996633": [
        287,
        215
    ],
    "#CC9900": [
        305,
        215
    ],
    "#FF9900": [
        323,
        215
    ],
    "#CC6600": [
        341,
        215
    ],
    "#FF3300": [
        359,
        215
    ],
    "#FF0000": [
        377,
        215
    ],
    "#CC0000": [
        395,
        215
    ],
    "#990033": [
        413,
        215
    ],
    "#663300": [
        296,
        200
    ],
    "#996600": [
        314,
        200
    ],
    "#CC3300": [
        332,
        200
    ],
    "#993300": [
        350,
        200
    ],
    "#990000": [
        368,
        200
    ],
    "#800000": [
        386,
        200
    ],
    "#993333": [
        404,
        200
    ]
}